LICENSE
MANIFEST.in
README.rst
dev-requirements.txt
release.py
setup.cfg
setup.py
tasks.py
test.conf.in
tox.ini
docs/Makefile
docs/conf.py
docs/index.rst
examples/common.py
examples/enforce_autostop.py
examples/startstop.py
images/centos.sh
lib/ravello_cli.py
lib/ravello_sdk.py
lib/ravello_sdk.egg-info/PKG-INFO
lib/ravello_sdk.egg-info/SOURCES.txt
lib/ravello_sdk.egg-info/dependency_links.txt
lib/ravello_sdk.egg-info/requires.txt
lib/ravello_sdk.egg-info/top_level.txt
tests/flow_application.py
tests/flow_diskimage.py
tests/flow_image.py
tests/flow_keypair.py
tests/flow_readall.py
tests/integration.py
tests/support.py
tests/test_functions.py
tests/unit.py