Metadata-Version: 1.1
Name: ravello-sdk
Version: 2.12
Summary: Python SDK for the Ravello API
Home-page: https://github.com/ravello/python-sdk
Author: Hadar Davidovich
Author-email: hadar.davidovich@oracle.com
License: Apache 2.0
Platform: UNKNOWN
Classifier: Development Status :: 5 - Production/Stable
Classifier: License :: OSI Approved :: Apache Software License
Classifier: Operating System :: POSIX
Classifier: Operating System :: MacOS :: MacOS X
Classifier: Operating System :: Microsoft :: Windows
Classifier: Programming Language :: Python :: 2.6
Classifier: Programming Language :: Python :: 2.7
Classifier: Programming Language :: Python :: 3.3
Classifier: Programming Language :: Python :: 3.4
